{
  "inheritFrom": "game:blocktypes/wood/woodtyped/log",
  "code": "log",

  "variantgroups": [
    {
      "code": "type",
      "states": [ "grown", "placed" ]
    },
    {
      "code": "wood",
      "states": [],
      "loadFromProperties": "bdtree:block/wood"
    },
    {
      "code": "rotation",
      "states": [ "ud", "ns", "we" ]
    }
  ],
  "sounds": {
    "place": "game:block/planks",
    "walk": "game:walk/wood",
    "hit": "game:block/planks",
    "break": "game:block/planks",
    "byTool": {
      "Axe": {
        "hit": "game:block/chop",
        "break": "game:block/planks"
      }
    }
  },
  "creativeinventory": {
    "general": [ "log-placed-*-ud" ],
    "flora": [ "log-placed-*-ud" ],
    "construction": [ "log-placed-*-ud" ],
    "bdtree": [ "log-placed-*-ud" ]
  },
  "shape": { "base": "game:block/basic/cube" },
  "texturesByType": {
    "*-ud": {
      "all": { "base": "block/wood/bark/{wood}" },
      "inside-north": {
        "base": "block/wood/debarked/{wood}",
        "rotation": 90
      },
      "inside-east": {
        "base": "block/wood/debarked/{wood}",
        "rotation": 90
      },
      "inside-south": {
        "base": "block/wood/debarked/{wood}",
        "rotation": 90
      },
      "inside-west": {
        "base": "block/wood/debarked/{wood}",
        "rotation": 90
      },

      "up": { "base": "block/wood/treetrunk/{wood}" },
      "down": { "base": "block/wood/treetrunk/{wood}" }
    },
    "*-ns": {
      "all": {
        "base": "block/wood/bark/{wood}",
        "rotation": 270
      },
      "up": { "base": "block/wood/bark/{wood}" },
      "down": { "base": "block/wood/bark/{wood}" },


      "inside-up": {
        "base": "block/wood/debarked/{wood}",
        "rotation": 90
      },
      "inside-down": {
        "base": "block/wood/debarked/{wood}",
        "rotation": 90
      },
      "inside-west": { "base": "block/wood/debarked/{wood}" },
      "inside-east": { "base": "block/wood/debarked/{wood}" },


      "north": { "base": "block/wood/treetrunk/{wood}" },
      "south": { "base": "block/wood/treetrunk/{wood}" }
    },
    "*-we": {
      "all": {
        "base": "block/wood/bark/{wood}",
        "rotation": 270
      },
      "up": {
        "base": "block/wood/bark/{wood}",
        "rotation": 270
      },

      "inside-up": { "base": "block/wood/debarked/{wood}" },
      "inside-down": { "base": "block/wood/debarked/{wood}" },
      "inside-north": { "base": "block/wood/debarked/{wood}" },
      "inside-south": { "base": "block/wood/debarked/{wood}" },


      "west": { "base": "block/wood/treetrunk/{wood}" },
      "east": { "base": "block/wood/treetrunk/{wood}" }
    }
  },
  "attributes": {
    "treeFellingGroupSpreadIndexByType": {
      "log-grown-willow-*": 3,
      "log-grown-douglasfir-*": 3,
      "log-grown-fir-*": 3,
      "log-grown-spruce-*": 3,
      "log-grown-sal-*": 3,
      "log-grown-empresstree-*": 3,
      "log-grown-mahogany-*": 3,
      "log-grown-spurgetree-*": 3,
      "log-grown-bluemahoe-*": 3,
      "log-grown-catalpa-*": 3,
      "log-grown-eucalyptus-*": 3,
      "log-grown-banyan-*": 3,
      "log-grown-mangrove-*": 3,
      "log-grown-satinash-*": 3,
      "log-grown-yew-*": 5,
      "log-grown-tuja-*": 5,
      "log-grown-elm-*": 5,
      "log-grown-tamanu-*": 5,
      "log-grown-guajacum-*": 5,
      "log-grown-dalbergia-*": 6,
      "log-grown-leadwood-*": 6,
      "log-grown-saxaul-*": 6,
      "log-grown-*": 4
    },
    "combustiblePropsByType": {
      "log-*-petrified-*": null,
      "log-*-bearnut-*": {
        "burnTemperature": 800,
        "burnDuration": 78
      },
      "log-*-saxaul-*": {
        "burnTemperature": 800,
        "burnDuration": 98
      },
      "log-*-elm-*": {
        "burnTemperature": 800,
        "burnDuration": 98
      },
      "log-*-sapele-*": {
        "burnTemperature": 800,
        "burnDuration": 98
      },
      "log-*-tigerwood-*": {
        "burnTemperature": 800,
        "burnDuration": 98
      },
      "log-*-tamanu-*": {
        "burnTemperature": 800,
        "burnDuration": 98
      },
      "log-*-dalbergia-*": {
        "burnTemperature": 800,
        "burnDuration": 110
      },
      "log-*-umnini-*": {
        "burnTemperature": 800,
        "burnDuration": 110
      },
      "log-*-leadwood-*": {
        "burnTemperature": 800,
        "burnDuration": 110
      },
      "log-*-yew-*": {
        "burnTemperature": 800,
        "burnDuration": 110
      },
      "log-*-tuja-*": {
        "meltingPoint": 100,
        "meltingDuration": 80,
        "smeltedRatio": 1,
        "smeltingType": "convert",
        "smeltedStack": {
          "type": "block",
          "code": "log-placed-charred-ud"
        },
        "requiresContainer": false,

        "burnTemperature": 800,
        "burnDuration": 110
      },
      "log-*-redcedar-*": {
        "meltingPoint": 100,
        "meltingDuration": 80,
        "smeltedRatio": 1,
        "smeltingType": "convert",
        "smeltedStack": {
          "type": "block",
          "code": "log-placed-charred-ud"
        },
        "requiresContainer": false,

        "burnTemperature": 800,
        "burnDuration": 110
      },
      "log-*-kauri-*": {
        "burnTemperature": 800,
        "burnDuration": 110
      },
      "log-*-cedar-*": {
        "meltingPoint": 100,
        "meltingDuration": 80,
        "smeltedRatio": 1,
        "smeltingType": "convert",
        "smeltedStack": {
          "type": "block",
          "code": "log-placed-charred-ud"
        },
        "requiresContainer": false,

        "burnTemperature": 800,
        "burnDuration": 60
      },
      "log-*-willow-*": {
        "burnTemperature": 700,
        "burnDuration": 70
      },
      "log-*-mangrove-*": {
        "burnTemperature": 700,
        "burnDuration": 70
      },
      "log-*-spurgetree-*": {
        "burnTemperature": 700,
        "burnDuration": 66
      },
      "log-*-guajacum-*": {
        "burnTemperature": 800,
        "burnDuration": 79
      },
      "log-*-eucalyptus-*": {
        "burnTemperature": 800,
        "burnDuration": 68
      },
      "log-*-douglasfir-*": {
        "burnTemperature": 800,
        "burnDuration": 68
      },
      "log-*-fir-*": {
        "burnTemperature": 800,
        "burnDuration": 68
      },
      "log-*-beech-*": {
        "burnTemperature": 800,
        "burnDuration": 89
      },
      "log-*-ash-*": {
        "burnTemperature": 800,
        "burnDuration": 89
      },
      "log-*-catalpa-*": {
        "burnTemperature": 800,
        "burnDuration": 54
      },
      "log-*-sal-*": {
        "burnTemperature": 800,
        "burnDuration": 54
      },
      "log-*-satinash-*": {
        "burnTemperature": 800,
        "burnDuration": 54
      },
      "log-*-banyan-*": {
        "burnTemperature": 800,
        "burnDuration": 58
      },
      "log-*-poplar-*": {
        "burnTemperature": 800,
        "burnDuration": 79
      },
      "log-*-empresstree-*": {
        "burnTemperature": 700,
        "burnDuration": 92
      },
      "log-*-honeylocust-*": {
        "burnTemperature": 700,
        "burnDuration": 92
      },
      "log-*-chlorociboria-*": {
        "burnTemperature": 700,
        "burnDuration": 40
      },
      "*": {
        "burnTemperature": 800,
        "burnDuration": 72
      }
    }
  }
}